oira.statistics.tools-1.0.0-py3.8-nspkg.pth
oira/statistics/tools/__init__.py
oira/statistics/tools/configure.zcml
oira/statistics/tools/scripts.py
oira/statistics/tools/update.py
oira/statistics/tools/utils.py
oira/statistics/tools/browser/__init__.py
oira/statistics/tools/browser/configure.zcml
oira/statistics/tools/browser/views.py
oira/statistics/tools/tests/__init__.py
oira/statistics/tools/tests/test_update_statistics.py
oira.statistics.tools-1.0.0.dist-info/LICENSE.txt
oira.statistics.tools-1.0.0.dist-info/METADATA
oira.statistics.tools-1.0.0.dist-info/WHEEL
oira.statistics.tools-1.0.0.dist-info/entry_points.txt
oira.statistics.tools-1.0.0.dist-info/namespace_packages.txt
oira.statistics.tools-1.0.0.dist-info/top_level.txt
oira.statistics.tools-1.0.0.dist-info/RECORD
